[
  {
    "jmeno": "Jiří Payne",
    "strana": "EFDD",
    "url": "url",
    "rank": "77%"
  },
  {
    "jmeno": "Petr Mach",
    "strana": "",
    "url": "",
    "rank": "56%"
  },
  {
    "jmeno": "Jan Zahradil",
    "strana": "",
    "url": "",
    "rank": "17%"
  },
  {
    "jmeno": "Evžen Tošenovský",
    "strana": "",
    "url": "",
    "rank": "12%"
  },
  {
    "jmeno": "Kateřina Konečná",
    "strana": "",
    "url": "",
    "rank": "-24%"
  },
  {
    "jmeno": "Miloslav Ransdorf",
    "strana": "",
    "url": "",
    "rank": "-25%"
  },
  {
    "jmeno": "Jaromír Kohlíček",
    "strana": "",
    "url": "",
    "rank": "-34%"
  },
  {
    "jmeno": "Martina Dlabajová",
    "strana": "",
    "url": "",
    "rank": "-35%"
  },
  {
    "jmeno": "Jiří Pospíšil",
    "strana": "",
    "url": "",
    "rank": "-35%"
  },
  {
    "jmeno": "Dita Charanzová",
    "strana": "",
    "url": "",
    "rank": "-37%"
  },
  {
    "jmeno": "Jiří Maštálka",
    "strana": "",
    "url": "",
    "rank": "-39%"
  },
  {
    "jmeno": "Tomáš Zdechovský",
    "strana": "",
    "url": "",
    "rank": "-40%"
  },
  {
    "jmeno": "Petr Ježek",
    "strana": "",
    "url": "",
    "rank": "-40%"
  },
  {
    "jmeno": "Michaela Šojdrová",
    "strana": "",
    "url": "",
    "rank": "-46%"
  },
  {
    "jmeno": "Pavel Telička",
    "strana": "",
    "url": "",
    "rank": "-46%"
  },
  {
    "jmeno": "Pavel Svoboda",
    "strana": "",
    "url": "",
    "rank": "-47%"
  },
  {
    "jmeno": "Stanislav Polčák",
    "strana": "",
    "url": "",
    "rank": "-50%"
  },
  {
    "jmeno": "Jaromír Štětina",
    "strana": "",
    "url": "",
    "rank": "-53%"
  },
  {
    "jmeno": "Luděk Niedermayer",
    "strana": "",
    "url": "",
    "rank": "-60%"
  },
  {
    "jmeno": "Olga Sehnalová",
    "strana": "",
    "url": "",
    "rank": "-61%"
  },
  {
    "jmeno": "Miroslav Poche",
    "strana": "",
    "url": "",
    "rank": "-61%"
  },
  {
    "jmeno": "Pavel Poc",
    "strana": "",
    "url": "",
    "rank": "-64%"
  },
  {
    "jmeno": "Jan Keller",
    "strana": "",
    "url": "",
    "rank": "-70%"
  }
]